{
	"gui_light": "front",
	"display": {
		"thirdperson_righthand": {
			"rotation": [0, 90, 0],
			"translation": [11, -2.25, 3.5]
		},
		"thirdperson_lefthand": {
			"rotation": [0, 90, 0],
			"translation": [11, -2.25, 3.5]
		},
		"firstperson_righthand": {
			"rotation": [177.95, 19.93, -175.52],
			"translation": [1.75, 0.75, 0],
			"scale": [0.68, 0.68, 0.68]
		},
		"firstperson_lefthand": {
			"rotation": [177.95, 19.93, -175.52],
			"translation": [1.75, 0.75, 0],
			"scale": [0.68, 0.68, 0.68]
		},
		"ground": {
			"translation": [0, 2.5, 4],
			"scale": [0.5, 0.5, 0.5]
		},
		"fixed": {
			"rotation": [0, 180, 0],
			"translation": [0, 0, -7.5]
		}
	},
	"groups": [
		{
			"name": "diamond_shield",
			"origin": [8, 8, 8],
			"color": 0,
			"children": [0, 1, 2, 3, 4, 5, 6, 7, 8, 9, 10, 11]
		},
		12
	],
	"overrides": [
		{
			"predicate": {
				"blocking": 1
			},
			"model": "dixtas_armory:item/diamond_shield_blocking"
		}
	]
}